tellabot/__init__.py
tellabot/cli.py
tellabot/utils.py
tellabot/templates/main_template/.env.example
tellabot/templates/main_template/.gitignore
tellabot/templates/main_template/README.md
tellabot/templates/main_template/requirements.txt
tellabot/templates/main_template/run.py
tellabot/templates/main_template/app/__init__.py
tellabot/templates/main_template/app/bot.py
tellabot/templates/main_template/app/handlers.py
tellabot-0.1.4.dist-info/METADATA
tellabot-0.1.4.dist-info/WHEEL
tellabot-0.1.4.dist-info/entry_points.txt
tellabot-0.1.4.dist-info/top_level.txt
tellabot-0.1.4.dist-info/RECORD
